setup.py
ejson/__init__.py
meteor_ejson.egg-info/PKG-INFO
meteor_ejson.egg-info/SOURCES.txt
meteor_ejson.egg-info/dependency_links.txt
meteor_ejson.egg-info/requires.txt
meteor_ejson.egg-info/top_level.txt