Metadata-Version: 1.1
Name: meteor-ejson
Version: 1.0.0
Summary: Encoder and Decoder for Extended JSON (EJSON) as used in Meteor and DDP.
Home-page: UNKNOWN
Author: Lars Schöning
Author-email: lars@lyschoening.de
License: MIT
Platform: UNKNOWN
Classifier: Environment :: Web Environment
Classifier: Intended Audience :: Developers
Classifier: License :: OSI Approved :: MIT License
Classifier: Operating System :: OS Independent
Classifier: Programming Language :: Python
Classifier: Programming Language :: Python :: 2.7
Classifier: Programming Language :: Python :: 3
Classifier: Programming Language :: Python :: 3.3
Classifier: Programming Language :: Python :: 3.4
Classifier: Topic :: Internet :: WWW/HTTP
Classifier: Topic :: Software Development :: Libraries :: Python Modules
